rtl/rtl/rtl/rtl/rtl/rtl/rtl/data_memory.v
module data_memory (
    input  wire        clk,
    input  wire [31:0] addr,
    input  wire [31:0] write_data,
    input  wire        mem_read,
    input  wire        mem_write,
    output reg  [31:0] read_data
);
    
    reg [31:0] mem [0:1023];
    
    wire [31:0] word_addr = addr >> 2;
    
    always @(*) begin
        if (mem_read)
            read_data = mem[word_addr[9:0]];
        else
            read_data = 32'h0;
    end
    
    always @(posedge clk) begin
        if (mem_write)
            mem[word_addr[9:0]] <= write_data;
    end
    
endmodule

rtl/rtl/rtl/rtl/rtl/rtl/alu_control.v
module alu_control (
    input  wire [3:0]  alu_op,
    input  wire [2:0]  funct3,
    input  wire [6:0]  funct7,
    output reg  [3:0]  alu_ctrl
);
    
    always @(*) begin
        case (alu_op)
            4'b0000: begin
                case ({funct7, funct3})
                    {7'b0000000, 3'b000}: alu_ctrl = 4'b0000;
                    {7'b0100000, 3'b000}: alu_ctrl = 4'b0001;
                    {7'b0000000, 3'b111}: alu_ctrl = 4'b0010;
                    {7'b0000000, 3'b110}: alu_ctrl = 4'b0011;
                    {7'b0000000, 3'b100}: alu_ctrl = 4'b0100;
                    {7'b0000000, 3'b001}: alu_ctrl = 4'b0101;
                    {7'b0000000, 3'b101}: alu_ctrl = 4'b0110;
                    {7'b0100000, 3'b101}: alu_ctrl = 4'b0111;
                    {7'b0000000, 3'b010}: alu_ctrl = 4'b1000;
                    default: alu_ctrl = 4'b0000;
                endcase
            end
            
            4'b0001: begin
                case (funct3)
                    3'b000: alu_ctrl = 4'b0000;
                    3'b111: alu_ctrl = 4'b0010;
                    3'b110: alu_ctrl = 4'b0011;
                    3'b100: alu_ctrl = 4'b0100;
                    3'b001: alu_ctrl = 4'b0101;
                    3'b101: alu_ctrl = (funct7[5]) ? 4'b0111 : 4'b0110;
                    3'b010: alu_ctrl = 4'b1000;
                    default: alu_ctrl = 4'b0000;
                endcase
            end
            
            4'b0010: alu_ctrl = 4'b0001;
            
            default: alu_ctrl = 4'b0000;
        endcase
    end
    
endmodule

rtl/rtl/rtl/rtl/rtl/control_unit.v
module control_unit (
    input  wire [6:0] opcode,
    input  wire [2:0] funct3,
    input  wire [6:0] funct7,
    input  wire       zero,
    output reg        reg_write,
    output reg        mem_read,
    output reg        mem_write,
    output reg        branch,
    output reg        jump,
    output reg        alu_src,
    output reg        mem_to_reg,
    output reg        pc_src,
    output reg [3:0]  alu_op
);
    
    always @(*) begin
        reg_write   = 1'b0;
        mem_read    = 1'b0;
        mem_write   = 1'b0;
        branch      = 1'b0;
        jump        = 1'b0;
        alu_src     = 1'b0;
        mem_to_reg  = 1'b0;
        pc_src      = 1'b0;
        alu_op      = 4'b0000;
        
        case (opcode)
            7'b0110011: begin
                reg_write = 1'b1;
            end
            
            7'b0010011: begin
                reg_write = 1'b1;
                alu_src = 1'b1;
                alu_op = 4'b0001;
            end
            
            7'b0000011: begin
                reg_write  = 1'b1;
                alu_src    = 1'b1;
                mem_read   = 1'b1;
                mem_to_reg = 1'b1;
            end
            
            7'b0100011: begin
                mem_write  = 1'b1;
                alu_src    = 1'b1;
            end
            
            7'b1100011: begin
                branch = (funct3 == 3'b000) ? zero : ~zero;
                alu_op = 4'b0010;
            end
            
            7'b1101111: begin
                reg_write = 1'b1;
                jump      = 1'b1;
                pc_src    = 1'b1;
            end
            
            7'b1100111: begin
                reg_write = 1'b1;
                jump      = 1'b1;
                pc_src    = 1'b1;
                alu_src   = 1'b1;
            end
        endcase
    end
    
endmodule

rtl/alu.v
module alu
#(
    parameter WIDTH = 32
)
(
    input  wire [WIDTH-1:0] A,
    input  wire [WIDTH-1:0] B,

    input  wire [3:0] ALUControl,

    output reg  [WIDTH-1:0] Result,

    output wire Zero,
    output wire Negative,
    output reg  Carry,
    output reg  Overflow
);
    
    localparam ALU_ADD  = 4'b0000;
    localparam ALU_SUB  = 4'b0001;
    localparam ALU_AND  = 4'b0010;
    localparam ALU_OR   = 4'b0011;
    localparam ALU_XOR  = 4'b0100;
    localparam ALU_SLL  = 4'b0101;
    localparam ALU_SRL  = 4'b0110;
    localparam ALU_SRA  = 4'b0111;
    localparam ALU_SLT  = 4'b1000;
    localparam ALU_SLTU = 4'b1001;
    
    always @(*) begin
        case (alu_op)
            ALU_ADD:  alu_result = operand_a + operand_b;
            ALU_SUB:  alu_result = operand_a - operand_b;
            ALU_AND:  alu_result = operand_a & operand_b;
            ALU_OR:   alu_result = operand_a | operand_b;
            ALU_XOR:  alu_result = operand_a ^ operand_b;
            ALU_SLL:  alu_result = operand_a << operand_b[4:0];
            ALU_SRL:  alu_result = operand_a >> operand_b[4:0];
            ALU_SRA:  alu_result = $signed(operand_a) >>> operand_b[4:0];
            ALU_SLT:  alu_result = ($signed(operand_a) < $signed(operand_b)) ? 32'h1 : 32'h0;
            ALU_SLTU: alu_result = (operand_a < operand_b) ? 32'h1 : 32'h0;
            default:  alu_result = 32'h0;
        endcase
    end
    
    assign zero = (alu_result == 32'h0);
    
endmodule

rtl/imm_generator.v
module imm_generator (
    input  wire [31:0] instr,
    output reg  [31:0] imm
);
    
    wire [6:0] opcode = instr[6:0];
    
    always @(*) begin
        case (opcode)
            7'b0010011, 7'b0000011, 7'b1100111: 
                imm = {{20{instr[31]}}, instr[31:20]};
            
            7'b0100011:
                imm = {{20{instr[31]}}, instr[31:25], instr[11:7]};
            
            7'b1100011:
                imm = {{19{instr[31]}}, instr[31], instr[7], instr[30:25], instr[11:8], 1'b0};
            
            7'b0110111, 7'b0010111:
                imm = {instr[31:12], 12'h0};
            
            7'b1101111:
                imm = {{11{instr[31]}}, instr[31], instr[19:12], instr[20], instr[30:21], 1'b0};
            
            default: imm = 32'h0;
        endcase
    end
    
endmodule

rtl/register_file.v
module register_file (
    input  wire        clk,
    input  wire        rst_n,
    input  wire [4:0]  rs1_addr,
    input  wire [4:0]  rs2_addr,
    input  wire [4:0]  rd_addr,
    input  wire [31:0] rd_data,
    input  wire        reg_write,
    output wire [31:0] rs1_data,
    output wire [31:0] rs2_data
);
    
    reg [31:0] regs [31:0];
    integer i;
    
    always @(posedge clk or negedge rst_n) begin
        if (!rst_n) begin
            for (i = 0; i < 32; i = i + 1)
                regs[i] <= 32'h0;
        end else if (reg_write && (rd_addr != 5'h0)) begin
            regs[rd_addr] <= rd_data;
        end
    end
    
    assign rs1_data = (rs1_addr == 5'h0) ? 32'h0 : regs[rs1_addr];
    assign rs2_data = (rs2_addr == 5'h0) ? 32'h0 : regs[rs2_addr];
    
endmodule

rtl/instruction_memory.v
module instruction_memory (
    input  wire        clk,
    input  wire [31:0] addr,
    output reg  [31:0] instr
);
    
    reg [31:0] mem [0:1023];
    
    initial begin
        $readmemh("programs/fibonacci.hex", mem);
    end
    
    wire [31:0] word_addr = addr >> 2;
    
    always @(posedge clk) begin
        instr <= mem[word_addr[9:0]];
    end
    
endmodule

rtl/pc.v
module pc (
    input  wire        clk,
    input  wire        rst_n,
    input  wire        pc_write,
    input  wire [31:0] next_pc,
    output reg  [31:0] pc_out
);
    
    always @(posedge clk or negedge rst_n) begin
        if (!rst_n)
            pc_out <= 32'h00000000;
        else if (pc_write)
            pc_out <= next_pc;
    end
    
endmodule

rtl/rtl/rtl/rtl/rtl/rtl/rtl/rtl/rtl/riscv_top.v
module riscv_top (
    input  wire        clk,
    input  wire        rst_n
);
    
    wire [31:0] pc, next_pc, pc_plus4;
    wire [31:0] instr;
    wire [31:0] imm;
    wire [31:0] rs1_data, rs2_data;
    wire [31:0] alu_result, alu_in2;
    wire [31:0] mem_read_data;
    wire [31:0] write_back_data;
    wire [3:0]  alu_ctrl;
    wire        zero;
    
    wire        reg_write, mem_read, mem_write;
    wire        branch, jump, alu_src, mem_to_reg, pc_src;
    wire [3:0]  alu_op;
    
    assign pc_plus4 = pc + 32'h4;
    assign next_pc = (pc_src) ? pc + imm : pc_plus4;
    
    pc u_pc (
        .clk(clk),
        .rst_n(rst_n),
        .pc_write(1'b1),
        .next_pc(next_pc),
        .pc_out(pc)
    );
    
    instruction_memory u_imem (
        .clk(clk),
        .addr(pc),
        .instr(instr)
    );
    
    register_file u_rf (
        .clk(clk),
        .rst_n(rst_n),
        .rs1_addr(instr[19:15]),
        .rs2_addr(instr[24:20]),
        .rd_addr(instr[11:7]),
        .rd_data(write_back_data),
        .reg_write(reg_write),
        .rs1_data(rs1_data),
        .rs2_data(rs2_data)
    );
    
    imm_generator u_imm (
        .instr(instr),
        .imm(imm)
    );
    
    assign alu_in2 = (alu_src) ? imm : rs2_data;
    
    alu u_alu (
        .operand_a(rs1_data),
        .operand_b(alu_in2),
        .alu_op(alu_ctrl),
        .alu_result(alu_result),
        .zero(zero)
    );
    
    control_unit u_ctrl (
        .opcode(instr[6:0]),
        .funct3(instr[14:12]),
        .funct7(instr[31:25]),
        .zero(zero),
        .reg_write(reg_write),
        .mem_read(mem_read),
        .mem_write(mem_write),
        .branch(branch),
        .jump(jump),
        .alu_src(alu_src),
        .mem_to_reg(mem_to_reg),
        .pc_src(pc_src),
        .alu_op(alu_op)
    );
    
    alu_control u_alu_ctrl (
        .alu_op(alu_op),
        .funct3(instr[14:12]),
        .funct7(instr[31:25]),
        .alu_ctrl(alu_ctrl)
    );
    
    data_memory u_dmem (
        .clk(clk),
        .addr(alu_result),
        .write_data(rs2_data),
        .mem_read(mem_read),
        .mem_write(mem_write),
        .read_data(mem_read_data)
    );
    
    assign write_back_data = (mem_to_reg) ? mem_read_data : alu_result;
    
endmodule

testbench/tb_riscv.v
`timescale 1ns/1ps

module tb_riscv;

reg clk;
reg rst_n;

integer total_tests;
integer passed_tests;
integer failed_tests;

real CPI;
real IPC;

riscv_top u_top(
    .clk(clk),
    .rst_n(rst_n)
);

always #5 clk = ~clk;

initial begin
    $dumpfile("waveform.vcd");
    $dumpvars(0,tb_riscv);
end

//------------------------------------------------------------
// PASS TASK
//------------------------------------------------------------
task pass;
input [255:0] msg;
begin
    total_tests = total_tests + 1;
    passed_tests = passed_tests + 1;
    $display("[PASS] %0s",msg);
end
endtask

//------------------------------------------------------------
// FAIL TASK
//------------------------------------------------------------
task fail;
input [255:0] msg;
begin
    total_tests = total_tests + 1;
    failed_tests = failed_tests + 1;
    $display("[FAIL] %0s",msg);
end
endtask

//------------------------------------------------------------
// SIMULATION
//------------------------------------------------------------
initial begin

    clk = 0;
    rst_n = 0;

    total_tests = 0;
    passed_tests = 0;
    failed_tests = 0;

    $display("");
    $display("===============================================");
    $display("        RV32I PROCESSOR VERIFICATION");
    $display("===============================================");

    #20;

    rst_n = 1;

    $display("Reset Released");

    #300;

    //--------------------------------------------------------
    // CHECKS
    //--------------------------------------------------------

    if(u_top.pc>0)
        pass("PC Running");
    else
        fail("PC Running");

    if(u_top.RegWrite===1'b0 || u_top.RegWrite===1'b1)
        pass("Control Unit");
    else
        fail("Control Unit");

    if(u_top.branch_taken===1'b0 || u_top.branch_taken===1'b1)
        pass("Branch Unit");
    else
        fail("Branch Unit");

    if(u_top.jump_taken===1'b0 || u_top.jump_taken===1'b1)
        pass("Jump Unit");
    else
        fail("Jump Unit");

    if(u_top.alu_result!==32'hxxxxxxxx)
        pass("ALU");
    else
        fail("ALU");

    if(u_top.cycle_count>0)
        pass("Cycle Counter");
    else
        fail("Cycle Counter");

    if(u_top.instruction_count>0)
        pass("Instruction Counter");
    else
        fail("Instruction Counter");

    //--------------------------------------------------------
    // PERFORMANCE
    //--------------------------------------------------------

    CPI = u_top.cycle_count;
    CPI = CPI / u_top.instruction_count;

    IPC = u_top.instruction_count;
    IPC = IPC / u_top.cycle_count;

    //--------------------------------------------------------
    // REPORT
    //--------------------------------------------------------

    $display("");

    $display("===============================================");
    $display("SIMULATION REPORT");
    $display("===============================================");

    $display("Cycle Count       : %0d",u_top.cycle_count);
    $display("Instruction Count : %0d",u_top.instruction_count);
    $display("CPI               : %0f",CPI);
    $display("IPC               : %0f",IPC);

    $display("");

    $display("Total Tests : %0d",total_tests);
    $display("Passed      : %0d",passed_tests);
    $display("Failed      : %0d",failed_tests);

    if(failed_tests==0)
        $display("STATUS : ALL TESTS PASSED");
    else
        $display("STATUS : TEST FAILED");

    $display("===============================================");

    #20;

    $finish;

end

//------------------------------------------------------------
// LIVE MONITOR
//------------------------------------------------------------
always @(posedge clk)
begin

    if(rst_n)
    begin

        $display("-------------------------------------------");
        $display("Time          : %0t",$time);
        $display("PC            : %h",u_top.pc);
        $display("Instruction   : %h",u_top.instr);
        $display("ALU Result    : %h",u_top.alu_result);
        $display("Branch Taken  : %b",u_top.branch_taken);
        $display("Jump Taken    : %b",u_top.jump_taken);
        $display("Cycles        : %0d",u_top.cycle_count);
        $display("Instructions  : %0d",u_top.instruction_count);
        $display("-------------------------------------------");

    end

end

endmodule

waveform.vcd
$date
	Tue Jun 30 23:56:03 2026
$end
$version
	Icarus Verilog
$end
$timescale
	1ps
$end
$scope module tb_riscv $end
$var reg 1 ! clk $end
$var reg 1 " rst_n $end
$scope module u_top $end
$var wire 1 ! clk $end
$var wire 1 " rst_n $end
$var wire 1 # zero $end
$var wire 32 $ write_back_data [31:0] $end
$var wire 32 % rs2_data [31:0] $end
$var wire 32 & rs1_data [31:0] $end
$var wire 1 ' reg_write $end
$var wire 1 ( pc_src $end
$var wire 32 ) pc_plus4 [31:0] $end
$var wire 32 * pc [31:0] $end
$var wire 32 + next_pc [31:0] $end
$var wire 1 , mem_write $end
$var wire 1 - mem_to_reg $end
$var wire 32 . mem_read_data [31:0] $end
$var wire 1 / mem_read $end
$var wire 1 0 jump $end
$var wire 32 1 instr [31:0] $end
$var wire 32 2 imm [31:0] $end
$var wire 1 3 branch $end
$var wire 1 4 alu_src $end
$var wire 32 5 alu_result [31:0] $end
$var wire 4 6 alu_op [3:0] $end
$var wire 32 7 alu_in2 [31:0] $end
$var wire 4 8 alu_ctrl [3:0] $end
$scope module u_alu $end
$var wire 32 9 operand_b [31:0] $end
$var wire 1 # zero $end
$var wire 32 : operand_a [31:0] $end
$var wire 4 ; alu_op [3:0] $end
$var parameter 4 < ALU_ADD $end
$var parameter 4 = ALU_AND $end
$var parameter 4 > ALU_OR $end
$var parameter 4 ? ALU_SLL $end
$var parameter 4 @ ALU_SLT $end
$var parameter 4 A ALU_SLTU $end
$var parameter 4 B ALU_SRA $end
$var parameter 4 C ALU_SRL $end
$var parameter 4 D ALU_SUB $end
$var parameter 4 E ALU_XOR $end
$var reg 32 F alu_result [31:0] $end
$upscope $end
$scope module u_alu_ctrl $end
$var wire 3 G funct3 [2:0] $end
$var wire 7 H funct7 [6:0] $end
$var wire 4 I alu_op [3:0] $end
$var reg 4 J alu_ctrl [3:0] $end
$upscope $end
$scope module u_ctrl $end
$var wire 3 K funct3 [2:0] $end
$var wire 7 L funct7 [6:0] $end
$var wire 7 M opcode [6:0] $end
$var wire 1 # zero $end
$var reg 4 N alu_op [3:0] $end
$var reg 1 4 alu_src $end
$var reg 1 3 branch $end
$var reg 1 0 jump $end
$var reg 1 / mem_read $end
$var reg 1 - mem_to_reg $end
$var reg 1 , mem_write $end
$var reg 1 ( pc_src $end
$var reg 1 ' reg_write $end
$upscope $end
$scope module u_dmem $end
$var wire 32 O addr [31:0] $end
$var wire 1 ! clk $end
$var wire 1 / mem_read $end
$var wire 1 , mem_write $end
$var wire 32 P write_data [31:0] $end
$var wire 32 Q word_addr [31:0] $end
$var reg 32 R read_data [31:0] $end
$upscope $end
$scope module u_imem $end
$var wire 1 ! clk $end
$var wire 32 S word_addr [31:0] $end
$var wire 32 T addr [31:0] $end
$var reg 32 U instr [31:0] $end
$upscope $end
$scope module u_imm $end
$var wire 32 V instr [31:0] $end
$var wire 7 W opcode [6:0] $end
$var reg 32 X imm [31:0] $end
$upscope $end
$scope module u_pc $end
$var wire 1 ! clk $end
$var wire 32 Y next_pc [31:0] $end
$var wire 1 Z pc_write $end
$var wire 1 " rst_n $end
$var reg 32 [ pc_out [31:0] $end
$upscope $end
$scope module u_rf $end
$var wire 1 ! clk $end
$var wire 5 \ rd_addr [4:0] $end
$var wire 32 ] rd_data [31:0] $end
$var wire 1 ' reg_write $end
$var wire 5 ^ rs1_addr [4:0] $end
$var wire 5 _ rs2_addr [4:0] $end
$var wire 1 " rst_n $end
$var wire 32 ` rs2_data [31:0] $end
$var wire 32 a rs1_data [31:0] $end
$var integer 32 b i [31:0] $end
$upscope $end
$upscope $end
$upscope $end
$enddefinitions $end
$comment Show the parameter values. $end
$dumpall
b100 E
b1 D
b110 C
b111 B
b1001 A
b1000 @
b101 ?
b11 >
b10 =
b0 <
$end
#0
$dumpvars
b100000 b
bx a
bx `
bx _
bx ^
bx ]
bx \
b0 [
1Z
bx Y
bx X
bx W
bx V
bx U
b0 T
b0 S
b0 R
b0xxxxxxxxxxxxxxxxxxxxxxxxxxxxxx Q
bx P
bx O
bx N
bx M
bx L
bx K
bx J
bx I
bx H
bx G
bx F
bx ;
bx :
bx 9
bx 8
bx 7
bx 6
bx 5
x4
x3
bx 2
bx 1
x0
x/
b0 .
x-
x,
bx +
b0 *
b100 )
x(
x'
bx &
bx %
bx $
x#
0"
0!
$end
#5000
b10 Q
b1010 $
b1010 ]
0#
b1010 5
b1010 F
b1010 O
b1010 7
b1010 9
b100 +
b100 Y
b0 8
b0 ;
b0 J
b1 6
b1 I
b1 N
0(
0-
14
00
03
0,
0/
1'
b0 %
b0 P
b0 `
b0 &
b0 :
b0 a
b1010 2
b1010 X
b10011 W
b0 H
b0 G
b0 L
b0 K
b10011 M
b1 \
b1010 _
b0 ^
b101000000000000010010011 1
b101000000000000010010011 U
b101000000000000010010011 V
b100000 b
1!
#10000
0!
#15000
b100000 b
1!
#20000
0!
1"
#25000
b1 S
b1000 +
b1000 Y
b1000 )
b100 *
b100 T
b100 [
1!
#30000
0!
#35000
b1 6
b1 I
b1 N
14
1'
b0 Q
b0 $
b0 ]
1#
b0 5
b0 F
b0 O
b0 7
b0 9
b0 2
b0 X
b10 \
b0 _
b10 S
b1100 +
b1100 Y
b100010011 1
b100010011 U
b100010011 V
b1100 )
b1000 *
b1000 T
b1000 [
1!
#40000
0!
#45000
b1 6
b1 I
b1 N
14
1'
b1 $
b1 ]
0#
b1 5
b1 F
b1 O
b1 7
b1 9
b1010 %
b1010 P
b1010 `
b1 2
b1 X
b11 \
b1 _
b11 S
b10000 +
b10000 Y
b100000000000110010011 1
b100000000000110010011 U
b100000000000110010011 V
b10000 )
b1100 *
b1100 T
b1100 [
1!
#50000
0!
#55000
b1 6
b1 I
b1 N
14
1'
b0 $
b0 ]
1#
b0 5
b0 F
b0 O
b0 7
b0 9
b0 %
b0 P
b0 `
b0 2
b0 X
b100 \
b0 _
b100 S
b10100 +
b10100 Y
b1000010011 1
b1000010011 U
b1000010011 V
b10100 )
b10000 *
b10000 T
b10000 [
1!
#60000
0!
#65000
b1 8
b1 ;
b1 J
13
b10 6
b10 I
b10 N
04
0'
b1000 2
b1000 X
b1100011 W
b1100011 M
b1000 \
b100 _
b100 ^
b101 S
b11000 +
b11000 Y
b10000100000010001100011 1
b10000100000010001100011 U
b10000100000010001100011 V
b11000 )
b10100 *
b10100 T
b10100 [
1!
#70000
0!
#75000
b1 $
b1 ]
0#
b1 5
b1 F
b1 O
b0 8
b0 ;
b0 J
b1 7
b1 9
1'
b0 6
b0 I
b0 N
03
b1 %
b1 P
b1 `
b0 2
b0 X
b110011 W
b110011 M
b101 \
b11 _
b10 ^
b110 S
b11100 +
b11100 Y
b1100010000001010110011 1
b1100010000001010110011 U
b1100010000001010110011 V
b11100 )
b11000 *
b11000 T
b11000 [
1!
#80000
0!
#85000
b1 $
b1 ]
b0 7
b0 9
b1 5
b1 F
b1 O
b0 %
b0 P
b0 `
b1 &
b1 :
b1 a
b100 \
b0 _
b11 ^
b111 S
b100000 +
b100000 Y
b11000001000110011 1
b11000001000110011 U
b11000001000110011 V
b100000 )
b11100 *
b11100 T
b11100 [
1!
#90000
0!
#95000
b11 \
b101 ^
b1000 S
b100100 +
b100100 Y
b101000000110110011 1
b101000000110110011 U
b101000000110110011 V
b100100 )
b100000 *
b100000 T
b100000 [
1!
#100000
0!
#105000
b10 $
b10 ]
b10 5
b10 F
b10 O
b1 7
b1 9
b1 6
b1 I
b1 N
14
1'
b1010 %
b1010 P
b1010 `
b1 2
b1 X
b10011 W
b10011 M
b100 \
b1 _
b100 ^
b1001 S
b101000 +
b101000 Y
b100100000001000010011 1
b100100000001000010011 U
b100100000001000010011 V
b101000 )
b100100 *
b100100 T
b100100 [
1!
#110000
0!
#115000
1#
b0 $
b0 ]
b0 7
b0 9
1(
10
b0 6
b0 I
b0 N
04
1'
b0 %
b0 P
b0 `
b0 5
b0 F
b0 O
b11111111111111111111111111111000 2
b11111111111111111111111111111000 X
b1101111 W
b1111111 H
b111 G
b1111111 L
b111 K
b1101111 M
b0 \
b11001 _
b11111 ^
b1010 S
b100000 +
b100000 Y
b0 &
b0 :
b0 a
b11111111100111111111000001101111 1
b11111111100111111111000001101111 U
b11111111100111111111000001101111 V
b101100 )
b101000 *
b101000 T
b101000 [
1!
#120000
0!
#125000
1(
10
1'
b0 2
b0 X
b0 H
b0 G
b0 L
b0 K
b0 _
b0 ^
b1000 S
b100000 +
b100000 Y
b1101111 1
b1101111 U
b1101111 V
b100100 )
b100000 *
b100000 T
b100000 [
1!
#130000
0!
#135000
b11 $
b11 ]
b1 7
b1 9
0#
b11 5
b11 F
b11 O
b100100 +
b100100 Y
b1 6
b1 I
b1 N
14
0(
00
1'
b1010 %
b1010 P
b1010 `
b10 &
b10 :
b10 a
b1 2
b1 X
b10011 W
b10011 M
b100 \
b1 _
b100 ^
b100100000001000010011 1
b100100000001000010011 U
b100100000001000010011 V
1!
#140000
0!
#145000
b1 Q
b100 $
b100 ]
b100 5
b100 F
b100 O
b11 &
b11 :
b11 a
b1001 S
b101000 +
b101000 Y
b101000 )
b100100 *
b100100 T
b100100 [
1!
#150000
0!
#155000
b0 Q
1#
b0 $
b0 ]
b0 7
b0 9
1(
10
b0 6
b0 I
b0 N
04
1'
b0 %
b0 P
b0 `
b0 5
b0 F
b0 O
b11111111111111111111111111111000 2
b11111111111111111111111111111000 X
b1101111 W
b1111111 H
b111 G
b1111111 L
b111 K
b1101111 M
b0 \
b11001 _
b11111 ^
b1010 S
b100000 +
b100000 Y
b0 &
b0 :
b0 a
b11111111100111111111000001101111 1
b11111111100111111111000001101111 U
b11111111100111111111000001101111 V
b101100 )
b101000 *
b101000 T
b101000 [
1!
#160000
0!
#165000
1(
10
1'
b0 2
b0 X
b0 H
b0 G
b0 L
b0 K
b0 _
b0 ^
b1000 S
b100000 +
b100000 Y
b1101111 1
b1101111 U
b1101111 V
b100100 )
b100000 *
b100000 T
b100000 [
1!
#170000
0!
#175000
b1 Q
b101 $
b101 ]
b1 7
b1 9
0#
b101 5
b101 F
b101 O
b100100 +
b100100 Y
b1 6
b1 I
b1 N
14
0(
00
1'
b1010 %
b1010 P
b1010 `
b100 &
b100 :
b100 a
b1 2
b1 X
b10011 W
b10011 M
b100 \
b1 _
b100 ^
b100100000001000010011 1
b100100000001000010011 U
b100100000001000010011 V
1!
#180000
0!
#185000
b110 $
b110 ]
b110 5
b110 F
b110 O
b101 &
b101 :
b101 a
b1001 S
b101000 +
b101000 Y
b101000 )
b100100 *
b100100 T
b100100 [
1!
#190000
0!
#195000
b0 Q
1#
b0 $
b0 ]
b0 7
b0 9
1(
10
b0 6
b0 I
b0 N
04
1'
b0 %
b0 P
b0 `
b0 5
b0 F
b0 O
b11111111111111111111111111111000 2
b11111111111111111111111111111000 X
b1101111 W
b1111111 H
b111 G
b1111111 L
b111 K
b1101111 M
b0 \
b11001 _
b11111 ^
b1010 S
b100000 +
b100000 Y
b0 &
b0 :
b0 a
b11111111100111111111000001101111 1
b11111111100111111111000001101111 U
b11111111100111111111000001101111 V
b101100 )
b101000 *
b101000 T
b101000 [
1!
#200000
0!
#205000
1(
10
1'
b0 2
b0 X
b0 H
b0 G
b0 L
b0 K
b0 _
b0 ^
b1000 S
b100000 +
b100000 Y
b1101111 1
b1101111 U
b1101111 V
b100100 )
b100000 *
b100000 T
b100000 [
1!
#210000
0!
#215000
b1 Q
b111 $
b111 ]
b1 7
b1 9
0#
b111 5
b111 F
b111 O
b100100 +
b100100 Y
b1 6
b1 I
b1 N
14
0(
00
1'
b1010 %
b1010 P
b1010 `
b110 &
b110 :
b110 a
b1 2
b1 X
b10011 W
b10011 M
b100 \
b1 _
b100 ^
b100100000001000010011 1
b100100000001000010011 U
b100100000001000010011 V
1!
